doctalk/__init__.py
doctalk/api.py
doctalk/down.py
doctalk/lemmas.json
doctalk/nlp.py
doctalk/params.py
doctalk/pypro.py
doctalk/refiner.py
doctalk/seek.py
doctalk/sim.py
doctalk/talk.py
doctalk/think.py
doctalk/vis.py
doctalk-0.4.0.dist-info/LICENSE
doctalk-0.4.0.dist-info/METADATA
doctalk-0.4.0.dist-info/WHEEL
doctalk-0.4.0.dist-info/top_level.txt
doctalk-0.4.0.dist-info/RECORD
