Metadata-Version: 2.1
Name: doctalk
Version: 0.4.0
Summary: doctalk: Dialogue agent handling queries about a given text document
Home-page: https://github.com/ptarau/pytalk.git
Author: Paul Tarau
License: Apache
License-File: LICENSE
Requires-Dist: networkx
Requires-Dist: nltk
Requires-Dist: graphviz
Requires-Dist: wordcloud
Requires-Dist: matplotlib
Requires-Dist: stanza
Requires-Dist: bert-extractive-summarizer
Requires-Dist: sumbert
Requires-Dist: Flask
Requires-Dist: waitress
Requires-Dist: natlog
